setup.py
erase_exif/__init__.py
erase_exif/cli.py
erase_exif/erase.py
erase_exif.egg-info/PKG-INFO
erase_exif.egg-info/SOURCES.txt
erase_exif.egg-info/dependency_links.txt
erase_exif.egg-info/entry_points.txt
erase_exif.egg-info/requires.txt
erase_exif.egg-info/top_level.txt