Metadata-Version: 1.1
Name: erase-exif
Version: 0.1.0
Summary: Erase exif meta data from your images
Home-page: https://github.com/bjarneo/python-erase-exif
Author: Bjarne Oeverli
Author-email: bjarne.oeverli@gmail.com
License: MIT
Download-URL: https://pypi.python.org/pypi/erase-exif
Keywords: erase exif image images
Platform: UNKNOWN
Classifier: Intended Audience :: End Users/Desktop
Classifier: Environment :: Console
Classifier: Operating System :: MacOS :: MacOS X
Classifier: Operating System :: POSIX
Classifier: Natural Language :: English
Classifier: Programming Language :: Python :: 3
Classifier: Programming Language :: Python :: 3.1
Classifier: Programming Language :: Python :: 3.2
Classifier: Programming Language :: Python :: 3.3
Classifier: Programming Language :: Python :: 3.4
Classifier: Programming Language :: Python :: 3.5
Classifier: Topic :: Terminals
